datapasta-1.0.0.dist-info/METADATA
datapasta-1.0.0.dist-info/WHEEL
datapasta-1.0.0.dist-info/entry_points.txt
datapasta-1.0.0.dist-info/licenses/LICENSE
datapasta/__init__.py
datapasta/clipboard.py
datapasta/clipboard_targets.py
datapasta/formatter.py
datapasta/html_parser.py
datapasta/main.py
datapasta/parser.py
datapasta/type_inference.py
datapasta-1.0.0.dist-info/RECORD
