Metadata-Version: 2.1
Name: datapasta
Version: 1.0.0
Summary: Paste data as Python DataFrame definitions
Author-Email: Louis Maddox <louismmx@gmail.com>
License: MIT
Classifier: Development Status :: 4 - Beta
Classifier: Intended Audience :: Developers
Classifier: License :: OSI Approved :: MIT License
Classifier: Natural Language :: English
Classifier: Operating System :: OS Independent
Classifier: Programming Language :: Python :: 3
Classifier: Programming Language :: Python :: 3.10
Classifier: Programming Language :: Python :: 3.11
Classifier: Programming Language :: Python :: 3.12
Classifier: Programming Language :: Python :: 3.13
Classifier: Programming Language :: Python :: Implementation :: CPython
Classifier: Programming Language :: Python
Project-URL: Bug Tracker, https://github.com/lmmx/datapasta/issues
Project-URL: Homepage, https://github.com/lmmx/datapasta
Requires-Python: >=3.10
Requires-Dist: cliptargets>=0.1.2
Provides-Extra: dev
Requires-Dist: pdm-bump>=0.9.10; extra == "dev"
Requires-Dist: pdm>=2.22.3; extra == "dev"
Requires-Dist: pre-commit>=4.1.0; extra == "dev"
Requires-Dist: pytest>=8.3.4; extra == "dev"
Provides-Extra: docs
Requires-Dist: livereload>=2.7.1; extra == "docs"
Requires-Dist: mkdocs-extra-sass-mathshim>=0.1.0; extra == "docs"
Requires-Dist: mkdocs-material[imaging,recommended]>=9.5.2; extra == "docs"
Requires-Dist: mkdocs-section-index>=0.3.8; extra == "docs"
Requires-Dist: mkdocs>=1.5.3; extra == "docs"
Requires-Dist: mkdocstrings[python]>=0.24.0; extra == "docs"
Requires-Dist: ruff>=0.9.5; extra == "docs"
Requires-Dist: urllib3<2; extra == "docs"
Provides-Extra: pandas
Requires-Dist: pandas>=2.2.3; extra == "pandas"
Provides-Extra: polars
Requires-Dist: polars>=1.21.0; extra == "polars"
Provides-Extra: polars-lts-cpu
Requires-Dist: polars-lts-cpu>=1.21.0; extra == "polars-lts-cpu"
Provides-Extra: pyperclip
Requires-Dist: pyperclip; extra == "pyperclip"
